cnoe_agent_utils/__init__.py
cnoe_agent_utils/llm_factory.py
cnoe_agent_utils/utils.py
cnoe_agent_utils/agents/README.md
cnoe_agent_utils/agents/__init__.py
cnoe_agent_utils/agents/base_langgraph_agent.py
cnoe_agent_utils/agents/base_langgraph_agent_executor.py
cnoe_agent_utils/agents/base_strands_agent.py
cnoe_agent_utils/agents/base_strands_agent_executor.py
cnoe_agent_utils/agents/context_config.py
cnoe_agent_utils/middleware/middleware.py
cnoe_agent_utils/tracing/__init__.py
cnoe_agent_utils/tracing/a2a_disabler.py
cnoe_agent_utils/tracing/a2a_utils.py
cnoe_agent_utils/tracing/decorators.py
cnoe_agent_utils/tracing/manager.py
cnoe_agent_utils-0.3.9.dist-info/METADATA
cnoe_agent_utils-0.3.9.dist-info/WHEEL
cnoe_agent_utils-0.3.9.dist-info/licenses/LICENSE
cnoe_agent_utils-0.3.9.dist-info/RECORD
