Metadata-Version: 2.4
Name: cnoe-agent-utils
Version: 0.3.9
Summary: Core utilities for CNOE agents including LLM factory, tracing, and base agent classes
Author-email: CNOE Contributors <cnoe-steering@googlegroups.com>
License-File: LICENSE
Keywords: agents,cnoe,llm,observability,tracing
Classifier: Development Status :: 4 - Beta
Classifier: Intended Audience :: Developers
Classifier: License :: OSI Approved :: Apache Software License
Classifier: Programming Language :: Python :: 3
Classifier: Programming Language :: Python :: 3.13
Classifier: Topic :: Software Development :: Libraries :: Python Modules
Requires-Python: <4.0,>=3.13
Requires-Dist: boto3>=1.34.0
Requires-Dist: botocore>=1.34.0
Requires-Dist: google-auth<3.0.0,>=2.40.2
Requires-Dist: google-cloud-aiplatform>=1.38.0
Requires-Dist: langchain-anthropic>=0.3.14
Requires-Dist: langchain-aws>=1.1.0
Requires-Dist: langchain-google-genai>=2.1.5
Requires-Dist: langchain-google-vertexai>=3.0.1
Requires-Dist: langchain-groq>=0.1.0
Requires-Dist: langchain-openai>=0.3.18
Requires-Dist: langfuse<4.0.0,>=3.0.0
Requires-Dist: opentelemetry-api>=1.20.0
Requires-Dist: opentelemetry-exporter-otlp>=1.20.0
Requires-Dist: opentelemetry-sdk>=1.20.0
Requires-Dist: pydantic>=2.0.0
Requires-Dist: python-dotenv>=1.1.0
Requires-Dist: tiktoken>=0.7.0
Requires-Dist: typing-extensions>=4.8.0
Provides-Extra: a2a
Requires-Dist: a2a-sdk>=0.1.0; extra == 'a2a'
Provides-Extra: agents
Requires-Dist: pydantic>=2.0.0; extra == 'agents'
Requires-Dist: tiktoken>=0.7.0; extra == 'agents'
Requires-Dist: typing-extensions>=4.8.0; extra == 'agents'
Provides-Extra: agents-all
Requires-Dist: a2a-sdk>=0.1.0; extra == 'agents-all'
Requires-Dist: langchain-core>=0.3.35; extra == 'agents-all'
Requires-Dist: langchain-mcp-adapters>=0.1.0; extra == 'agents-all'
Requires-Dist: langgraph>=0.2.70; extra == 'agents-all'
Requires-Dist: pydantic>=2.0.0; extra == 'agents-all'
Requires-Dist: strands>=0.1.0; extra == 'agents-all'
Requires-Dist: tiktoken>=0.7.0; extra == 'agents-all'
Requires-Dist: typing-extensions>=4.8.0; extra == 'agents-all'
Provides-Extra: anthropic
Requires-Dist: langchain-anthropic>=0.3.14; extra == 'anthropic'
Provides-Extra: aws
Requires-Dist: boto3>=1.34.0; extra == 'aws'
Requires-Dist: botocore>=1.34.0; extra == 'aws'
Requires-Dist: langchain-aws>=1.1.0; extra == 'aws'
Provides-Extra: azure
Requires-Dist: langchain-openai>=0.3.18; extra == 'azure'
Provides-Extra: dev
Requires-Dist: commitizen>=4.8.3; extra == 'dev'
Requires-Dist: mypy>=1.0.0; extra == 'dev'
Requires-Dist: pip>=25.1.1; extra == 'dev'
Requires-Dist: pytest-asyncio>=0.21.0; extra == 'dev'
Requires-Dist: pytest-cov>=4.0.0; extra == 'dev'
Requires-Dist: pytest>=8.0.0; extra == 'dev'
Requires-Dist: ruff>=0.1.0; extra == 'dev'
Provides-Extra: gcp
Requires-Dist: google-auth<3.0.0,>=2.40.2; extra == 'gcp'
Requires-Dist: google-cloud-aiplatform>=1.38.0; extra == 'gcp'
Requires-Dist: langchain-google-genai>=2.1.5; extra == 'gcp'
Requires-Dist: langchain-google-vertexai>=3.0.1; extra == 'gcp'
Provides-Extra: groq
Requires-Dist: langchain-groq>=0.1.0; extra == 'groq'
Provides-Extra: langgraph
Requires-Dist: langchain-core>=0.3.35; extra == 'langgraph'
Requires-Dist: langchain-mcp-adapters>=0.1.0; extra == 'langgraph'
Requires-Dist: langgraph>=0.2.70; extra == 'langgraph'
Provides-Extra: openai
Requires-Dist: langchain-openai>=0.3.18; extra == 'openai'
Provides-Extra: strands
Requires-Dist: strands>=0.1.0; extra == 'strands'
Provides-Extra: tracing
Requires-Dist: langfuse<4.0.0,>=3.0.0; extra == 'tracing'
Requires-Dist: opentelemetry-api>=1.20.0; extra == 'tracing'
Requires-Dist: opentelemetry-exporter-otlp>=1.20.0; extra == 'tracing'
Requires-Dist: opentelemetry-sdk>=1.20.0; extra == 'tracing'
